{
"01":{ "category":"ACCIDENT - CONSTRUCTION/PLUMBING" ,"priority":"A"},
"03":{ "category":"ADJACENT BUILDINGS - NOT PROTECTED" ,"priority":"A"},
"04":{ "category":"AFTER HOURS WORK - ILLEGAL" ,"priority":"B"},
"05":{ "category":"PERMIT - NONE (BUILDING/ PA/ DEMO ETC.)" ,"priority":"B"},
"06":{ "category":"CONSTRUCTION - CHANGE GRADE / CHANGE WATERCOURSE" ,"priority":"B"},
"09":{ "category":"DEBRIS - EXCESSIVE" ,"priority":"B"},
"10":{ "category":"DEBRIS/BUILDING -FALLING OR IN DANGER OF FALLING" ,"priority":"A"},
"12":{ "category":"DEMOLITION-UNSAFE/ILLEGAL/MECHANICAL DEMO" ,"priority":"A"},
"13":{ "category":"ELEVATOR IN (FDNY) READINESS-NONE" ,"priority":"A"},
"14":{ "category":"EXCAVATION - UNDERMINING ADJACENT BUILDING" ,"priority":"A"},
"15":{ "category":"FENCE - NONE/INADEQUATE/ILLEGAL" ,"priority":"B"},
"16":{ "category":"INADEQUATE SUPPORT/SHORING" ,"priority":"A"},
"18":{ "category":"MATERIAL STORAGE - UNSAFE" ,"priority":"A"},
"20":{ "category":"LANDMARK BUILDING - ILLEGAL WORK" ,"priority":"A"},
"21":{ "category":"SAFETY NET/GUARD RAIL-DAMAGED/INADEQUATE/NONE(OVER 6 STY/75 FT)" ,"priority":"B"},
"23":{ "category":"SIDEWALK SHED/SUPPORTED SCAFFOLD/ INADEQUATE/ DEFECTIVE/ NONE/NOPMT/NO CERT" ,"priority":"B"},
"29":{ "category":"BUILDING - VACANT, OPEN AND UNGUARDED" ,"priority":"C"},
"30":{ "category":"BUILDING SHAKING/VIBRATING/STRUCT STABILITY AFFECTED" ,"priority":"A"},
"31":{ "category":"CERTIFICATE OF OCCUPANCY - NONE/ILLEGAL/CONTRARY TO CO" ,"priority":"C"},
"35":{ "category":"CURB CUT/DRIVEWAY/CARPORT - ILLEGAL" ,"priority":"D"},
"37":{ "category":"EGRESS - LOCKED/BLOCKED/IMPROPER/NO SECONDARY MEANS" ,"priority":"A"},
"45":{ "category":"ILLEGAL CONVERSION" ,"priority":"B"},
"49":{ "category":"STOREFRONT OR BUSINESS SIGN/AWNING/MARQUEE/CANOPY – ILLEGAL" ,"priority":"C"},
"50":{ "category":"SIGN FALLING - DANGER/SIGN ERECTION OR DISPLAY IN PROGRESS – ILLEGAL" ,"priority":"A"},
"52":{ "category":"SPRINKLER SYSTEM - INADEQUATE" ,"priority":"B"},
"53":{ "category":"VENT/EXHAUST - ILLEGAL/IMPROPER" ,"priority":"D"},
"54":{ "category":"WALL/RETAINING WALL - BULGING/CRACKED" ,"priority":"B"},
"55":{ "category":"ZONING - NON-CONFORMING" ,"priority":"D"},
"56":{ "category":"BOILER - FUMES/SMOKE/CARBON MONOXIDE" ,"priority":"A"},
"58":{ "category":"BOILER - DEFECTIVE / INOPERATIVE / NO PERMIT" ,"priority":"B"},
"59":{ "category":"ELECTRICAL WIRING – DEFECTIVE / EXPOSED, IN PROGRESS" ,"priority":"B"},
"62":{ "category":"ELEVATOR-DANGER CONDITION/SHAFT OPEN/UNGUARDED" ,"priority":"A"},
"63":{ "category":"ELEVATOR - DEFECTIVE / INOPERATIVE" ,"priority":"B"},
"65":{ "category":"GAS HOOK-UP/PIPING - ILLEGAL OR DEFECTIVE" ,"priority":"A"},
"66":{ "category":"PLUMBING WORK - ILLEGAL/NO PERMIT(ALSO SPRINKLER/STANDPIPE)" ,"priority":"B"},
"67":{ "category":"CRANE - NO PERMIT/LICENSE/CERT/UNSAFE/ILLEGAL" ,"priority":"A"},
"71":{ "category":"SRO - ILLEGAL WORK/NO PERMIT/CHANGE IN OCCUP-USE" ,"priority":"B"},
"73":{ "category":"FAILURE TO MAINTAIN" ,"priority":"C"},
"74":{ "category":"ILLEGAL COMMERCIAL/MANUFACTURING USE IN RESIDENTIAL ZONE" ,"priority":"C"},
"75":{ "category":"ADULT ESTABLISHMENT" ,"priority":"B"},
"76":{ "category":"UNLICENSED/ILLEGAL/IMPROPER PLUMBING WORK IN PROGRESS" ,"priority":"A"},
"77":{ "category":"CONTRARY TO LL58/87 (HANDICAP ACCESS)" ,"priority":"C"},
"78":{ "category":"PRIVATELY OWNED PUBLIC SPACE/NON-COMPLIANCE" ,"priority":"B"},
"79":{ "category":"LIGHTS FROM PARKING LOT SHINING ON BUILDING" ,"priority":"C"},
"80":{ "category":"ELEVATOR NOT INSPECTED/ILLEGAL/NO PERMIT" ,"priority":"D"},
"81":{ "category":"ELEVATOR - ACCIDENT" ,"priority":"A"},
"82":{ "category":"BOILER - ACCIDENT/EXPLOSION" ,"priority":"A"},
"83":{ "category":"CONSTRUCTION -CONTRARY/BEYOND APPROVED PLANS/PERMITS" ,"priority":"B"},
"85":{ "category":"FAILURE TO RETAIN WATER / IMPROPER DRAINAGE (LL103/89)" ,"priority":"C"},
"86":{ "category":"WORK CONTRARY TO STOP WORK ORDER" ,"priority":"A"},
"88":{ "category":"SAFETY NET/GUARD RAIL-DAM/INADEQ/NONE(6FL.75 FT OR LESS)" ,"priority":"B"},
"89":{ "category":"ACCIDENT-CRANES/DERRICKS/SUSPENSION" ,"priority":"A"},
"90":{ "category":"UNLICENSED/ILLEGAL ACTIVITY" ,"priority":"C"},
"91":{ "category":"SITE CONDITIONS ENDANGERING WORKERS" ,"priority":"A"},
"92":{ "category":"ILLEGAL CONVERSION OF MANUFACTURING/INDUSTRIAL SPACE" ,"priority":"B"},
"93":{ "category":"REQUEST FOR RETAINING WALL SAFETY INSPECTION" ,"priority":"B"},
"94":{ "category":"PLUMBING-DEFECTIVE/LEAKING/NOT MAINTAINED" ,"priority":"C"},
"1A":{ "category":"ILLEGAL CONVERSION COMMERCIAL BLDG/SPACE TO DWELLING UNITS" ,"priority":"B"},
"1B":{ "category":"ILLEGAL TREE REMOVAL/TOPO. CHANGE IN SNAD" ,"priority":"B"},
"1D":{ "category":"CON EDISON REFERRAL" ,"priority":"B"},
"1E":{ "category":"SUSPENDED (HANGING) SCAFFOLDS- NO PMT/LIC/DANGEROUS/ACCIDENT" ,"priority":"A"},
"1G":{ "category":"STALLED CONSTRUCTION SITE" ,"priority":"B"},
"1K":{ "category":"BOWSTRING TRUSS TRACKING COMPLAINT" ,"priority":"D"},
"1Z":{ "category":"ENFORCEMENT WORK ORDER (DOB)" ,"priority":"D"},
"2A":{ "category":"POSTED NOTICE OR ORDER REMOVED/TAMPERED WITH" ,"priority":"B"},
"2B":{ "category":"FAILURE TO COMPLY WITH VACATE ORDER" ,"priority":"A"},
"2C":{ "category":"SMOKING BAN – SMOKING ON CONSTRUCTION SITE" ,"priority":"B"},
"2D":{ "category":"SMOKING SIGNS – “NO SMOKING SIGNS” NOT OBSERVED ON CONSTRUCTION SITE" ,"priority":"B"},
"2E":{ "category":"DEMOLITION NOTIFICATION RECEIVED" ,"priority":"A"},
"2F":{ "category":"BUILDING UNDER STRUCTURAL MONITORING" ,"priority":"D"},
"2G":{ "category":"ADVERTISING SIGN/BILLBOARD/POSTERS/FLEXIBLE FABRIC – ILLEGAL" ,"priority":"C"},
"2H":{ "category":"SECOND AVENUE SUBWAY CONSTRUCTION" ,"priority":"D"},
"2J":{ "category":"SANDY: BUILDING DESTROYED" ,"priority":"D"},
"2K":{ "category":"STRUCTURALLY COMPROMISED BUILDING (LL33/08)" ,"priority":"D"},
"2L":{ "category":"FAÇADE (LL11/98)- UNSAFE NOTIFICATION" ,"priority":"D"},
"2M":{ "category":"MONOPOLE TRACKING COMPLAINT" ,"priority":"D"},
"3A":{ "category":"UNLICENSED/ILLEGAL/IMPROPER ELECTRICAL WORK IN PROGRESS" ,"priority":"B"},
"4A":{ "category":"ILLEGAL HOTEL ROOMS IN RESIDENTIAL BUILDINGS" ,"priority":"B"},
"4B":{ "category":"SEP - PROFESSIONAL CERTIFICATION COMPLIANCE AUDIT" ,"priority":"B"},
"4C":{ "category":"EXCAVATION TRACKING COMPLAINT" ,"priority":"D"},
"4D":{ "category":"INTERIOR DEMO TRACKING COMPLAINT" ,"priority":"D"},
"4F":{ "category":"SST TRACKING COMPLAINT" ,"priority":"D"},
"4G":{ "category":"ILLEGAL CONVERSION NO ACCESS FOLLOW-UP" ,"priority":"B"},
"4J":{ "category":"M.A.R.C.H. PROGRAM (INTERAGENCY)" ,"priority":"D"},
"4K":{ "category":"BEST - DM TRACKING COMPLAINT" ,"priority":"D"},
"4L":{ "category":"BEST - HIGH-RISE TRACKING COMPLAINT" ,"priority":"D"},
"4M":{ "category":"BEST - LOW-RISE TRACKING COMPLAINT" ,"priority":"D"},
"4N":{ "category":"RETAINING WALL TRACKING COMPLAINT" ,"priority":"D"},
"4P":{ "category":"LEGAL/PADLOCK TRACKING COMPLAINT" ,"priority":"D"},
"4W":{ "category":"WOODSIDE SETTLEMENT PROJECT" ,"priority":"C"},
"5A":{ "category":"REQUEST FOR JOINT FDNY/DOB INSPECTION" ,"priority":"B"},
"5B":{ "category":"NON-COMPLIANCE W/LIGHTWEIGHT MATERIALS" ,"priority":"A"},
"5C":{ "category":"STRUCTURAL STABILITY IMPACTED - NEW BUILDING UNDER CONSTRUCTION" ,"priority":"A"},
"5E":{ "category":"AMUSEMENT RIDE ACCIDENT/INCIDENT" ,"priority":"A"},
"5F":{ "category":"COMPLIANCE INSPECTION" ,"priority":"B"},
"5G":{ "category":"UNLICENSED/ILLEGAL/IMPROPER WORK IN PROGRESS" ,"priority":"B"},
"6A":{ "category":"VESTING INSPECTION" ,"priority":"C"}}